LICENSE
MANIFEST.in
README.md
pyproject.toml
setup.cfg
setup.py
tests/__init__.py
tests/testapp/__init__.py
tests/testapp/manage.py
tests/testapp/core/__init__.py
tests/testapp/core/tests.py
tests/testapp/core/migrations/__init__.py
tests/testapp/testapp/__init__.py
tests/testapp/testapp/asgi.py
tests/testapp/testapp/settings.py
tests/testapp/testapp/urls.py
tests/testapp/testapp/wsgi.py
wagtail_ace_editor/__init__.py
wagtail_ace_editor/apps.py
wagtail_ace_editor/blocks.py
wagtail_ace_editor/clean.py
wagtail_ace_editor/forms.py
wagtail_ace_editor/util.py
wagtail_ace_editor/wagtail_hooks.py
wagtail_ace_editor/widgets.py
wagtail_ace_editor.egg-info/PKG-INFO
wagtail_ace_editor.egg-info/SOURCES.txt
wagtail_ace_editor.egg-info/dependency_links.txt
wagtail_ace_editor.egg-info/requires.txt
wagtail_ace_editor.egg-info/top_level.txt
wagtail_ace_editor/migrations/__init__.py
wagtail_ace_editor/migrations/__pycache__/__init__.cpython-311.pyc
wagtail_ace_editor/static/wagtail_ace_editor/css/ace-editor-iframe.css
wagtail_ace_editor/static/wagtail_ace_editor/css/ace-editor-widget.css
wagtail_ace_editor/static/wagtail_ace_editor/js/LICENSE
wagtail_ace_editor/static/wagtail_ace_editor/js/ace-editor-controller.js
wagtail_ace_editor/static/wagtail_ace_editor/js/ace-editor-telepath.js
wagtail_ace_editor/static/wagtail_ace_editor/js/ace-editor.js
wagtail_ace_editor/static/wagtail_ace_editor/js/ace.js
wagtail_ace_editor/static/wagtail_ace_editor/js/ext-beautify.js
wagtail_ace_editor/static/wagtail_ace_editor/js/ext-code_lens.js
wagtail_ace_editor/static/wagtail_ace_editor/js/ext-command_bar.js
wagtail_ace_editor/static/wagtail_ace_editor/js/ext-elastic_tabstops_lite.js
wagtail_ace_editor/static/wagtail_ace_editor/js/ext-emmet.js
wagtail_ace_editor/static/wagtail_ace_editor/js/ext-error_marker.js
wagtail_ace_editor/static/wagtail_ace_editor/js/ext-hardwrap.js
wagtail_ace_editor/static/wagtail_ace_editor/js/ext-inline_autocomplete.js
wagtail_ace_editor/static/wagtail_ace_editor/js/ext-keybinding_menu.js
wagtail_ace_editor/static/wagtail_ace_editor/js/ext-language_tools.js
wagtail_ace_editor/static/wagtail_ace_editor/js/ext-linking.js
